raster2points/__init__.py
raster2points/raster2csv.py
raster2points/raster2points.py
raster2points-0.1.9.data/scripts/raster2csv.py
raster2points-0.1.9.dist-info/LICENSE
raster2points-0.1.9.dist-info/METADATA
raster2points-0.1.9.dist-info/WHEEL
raster2points-0.1.9.dist-info/top_level.txt
raster2points-0.1.9.dist-info/RECORD
