Metadata-Version: 2.1
Name: raster2points
Version: 0.1.9
Summary: Tool to convert rasters to points
Home-page: https://github.com/wri/raster2points
Author: Thomas Maschler
Author-email: thomas.maschler@wri.org
License: MIT
Platform: UNKNOWN
Classifier: Programming Language :: Python :: 3
Classifier: License :: OSI Approved :: MIT License
Classifier: Operating System :: OS Independent
Requires-Dist: numba (~=0.49.1)
Requires-Dist: pandas (~=0.24.2)
Requires-Dist: parallelpipe (~=0.2.6)
Requires-Dist: rasterio[s3] (~=1.0.28)
